shortcake/__init__.py
shortcake/cli.py
shortcake/config.py
shortcake-0.1.0.dist-info/METADATA
shortcake-0.1.0.dist-info/WHEEL
shortcake-0.1.0.dist-info/entry_points.txt
shortcake-0.1.0.dist-info/licenses/LICENSE
shortcake-0.1.0.dist-info/RECORD
