Metadata-Version: 2.4
Name: shortcake
Version: 0.1.0
Summary: A CLI built with typer and uv
License-File: LICENSE
Requires-Python: >=3.14
Requires-Dist: pydantic>=2.0.0
Requires-Dist: rtoml>=0.11.0
Requires-Dist: typer>=0.9.0
